git_jira/__init__.py
git_jira/cli.py
git_jira/config.py
git_jira/git.py
git_jira/jira.py
git_jira/utils.py
git_jira/commands/__init__.py
git_jira/commands/branch.py
git_jira/commands/configure.py
git_jira/commands/issue.py
git_jira/commands/list.py
git_jira-0.5.0.dist-info/LICENSE.txt
git_jira-0.5.0.dist-info/METADATA
git_jira-0.5.0.dist-info/WHEEL
git_jira-0.5.0.dist-info/entry_points.txt
git_jira-0.5.0.dist-info/top_level.txt
git_jira-0.5.0.dist-info/RECORD
