Metadata-Version: 2.1
Name: git-jira
Version: 0.5.0
Summary: A git addon to manage Jira from git
Home-page: https://github.com/rloredo/git-jira
Author: rloredo
Author-email: loredo.rod@gmail.com
License: MIT
Classifier: Development Status :: 3 - Alpha
Classifier: License :: OSI Approved :: MIT License
Classifier: Operating System :: Microsoft :: Windows
Classifier: Operating System :: MacOS :: MacOS X
Classifier: Operating System :: POSIX :: Linux
Classifier: Programming Language :: Python :: 3.6
Classifier: Programming Language :: Python :: 3.7
Classifier: Programming Language :: Python :: 3.8
Classifier: Programming Language :: Python :: 3.9
Requires-Python: >=3.6.2
License-File: LICENSE.txt
Requires-Dist: click (==8.0)
Requires-Dist: jira (==3.4)
Requires-Dist: PyYAML (==6.0)
Requires-Dist: sh (==1.14)
Requires-Dist: pick (==2.0)
Requires-Dist: prettytable (==3.4)
Provides-Extra: dev
Requires-Dist: tox (==3.26) ; extra == 'dev'
Requires-Dist: pytest (==7.1) ; extra == 'dev'
Requires-Dist: mypy (==0.981) ; extra == 'dev'
Requires-Dist: black (==22.8) ; extra == 'dev'
Requires-Dist: pylint (==2.15) ; extra == 'dev'
Requires-Dist: isort (==5.10.1) ; extra == 'dev'
